mdformat_hatena/__init__.py
mdformat_hatena/plugin.py
mdformat_hatena-0.2.0.dist-info/METADATA
mdformat_hatena-0.2.0.dist-info/WHEEL
mdformat_hatena-0.2.0.dist-info/entry_points.txt
mdformat_hatena-0.2.0.dist-info/top_level.txt
mdformat_hatena-0.2.0.dist-info/RECORD
