Metadata-Version: 2.1
Name: mdformat-hatena
Version: 0.2.0
Summary: mdformat for Hatena Blog markdown.
Author: ZenProducts Inc.
License: MIT
Requires-Dist: mdformat (>=0.7)
